geospin_utilities-1.3.3-py3.7-nspkg.pth
geospin/utilities/__init__.py
geospin/utilities/backend.py
geospin/utilities/decorators.py
geospin/utilities/geometry.py
geospin/utilities/misc.py
geospin/utilities/mlflow.py
geospin/utilities/pandas_utils.py
geospin/utilities/tiling.py
geospin/utilities/api/__init__.py
geospin/utilities/api/populator.py
geospin/utilities/feature/__init__.py
geospin/utilities/feature/addition.py
geospin/utilities/feature/probing.py
geospin/utilities/h3/__init__.py
geospin/utilities/h3/misc.py
geospin/utilities/h3/parents.py
geospin/utilities/h3/polyfill.py
geospin/utilities/visualization/__init__.py
geospin/utilities/visualization/maps.py
tests/integration/__init__.py
tests/integration/geospin/__init__.py
tests/integration/geospin/utilities/__init__.py
tests/integration/geospin/utilities/conftest.py
tests/integration/geospin/utilities/test_backend.py
tests/integration/geospin/utilities/test_geometry.py
tests/integration/geospin/utilities/test_misc.py
tests/integration/geospin/utilities/test_mlflow.py
tests/integration/geospin/utilities/test_pandas_utils.py
tests/integration/geospin/utilities/test_tiling.py
tests/integration/geospin/utilities/api/__init__.py
tests/integration/geospin/utilities/api/test_populator.py
tests/integration/geospin/utilities/feature/__init__.py
tests/integration/geospin/utilities/feature/test_addition.py
tests/integration/geospin/utilities/feature/test_probing.py
tests/integration/geospin/utilities/h3/__init__.py
tests/integration/geospin/utilities/h3/test_misc.py
tests/integration/geospin/utilities/h3/test_parents.py
tests/integration/geospin/utilities/h3/test_polyfill.py
tests/integration/geospin/utilities/visualization/__init__.py
tests/integration/geospin/utilities/visualization/test_maps.py
geospin_utilities-1.3.3.dist-info/LICENSE
geospin_utilities-1.3.3.dist-info/METADATA
geospin_utilities-1.3.3.dist-info/WHEEL
geospin_utilities-1.3.3.dist-info/namespace_packages.txt
geospin_utilities-1.3.3.dist-info/top_level.txt
geospin_utilities-1.3.3.dist-info/RECORD
