Metadata-Version: 2.1
Name: geospin-utilities
Version: 1.3.3
Summary: Geo-processing utility functions
Home-page: UNKNOWN
Author: Geospin GmbH
Author-email: it@geospin.de
License: GNU General Public License v3.0
Platform: UNKNOWN
Requires-Python: >=3.6
Requires-Dist: numpy (>=1.18.1)
Requires-Dist: scikit-learn (>=0.22.1)
Requires-Dist: shapely (>=1.7.0)
Requires-Dist: pyproj (>=2.4.2.post1)
Requires-Dist: pandas (>=1.0.1)
Requires-Dist: folium (>=0.10.1)
Requires-Dist: matplotlib (>=3.1.3)
Requires-Dist: geopandas (>=0.7.0)
Requires-Dist: fiona (>=1.8.13)
Requires-Dist: h3 (>=3.6.3)
Requires-Dist: branca (>=0.3.1)
Requires-Dist: geojson (>=2.5.0)
Requires-Dist: sqlalchemy (>=1.3.12)
Requires-Dist: psycopg2-binary (>=2.8.4)
Requires-Dist: mlflow (>=1.11.0)
